semgrep_discovery/__init__.py
semgrep_discovery/config.py
semgrep_discovery/main.py
semgrep_discovery/result_writer.py
semgrep_discovery/rules/java/dto.yaml
semgrep_discovery/rules/python/dto.yaml
semgrep_discovery/rules/python/route.yaml
semgrep_discovery/semgrep_runner.py
semgrep_discovery-0.4.5.dist-info/METADATA
semgrep_discovery-0.4.5.dist-info/WHEEL
semgrep_discovery-0.4.5.dist-info/entry_points.txt
semgrep_discovery-0.4.5.dist-info/RECORD
